qujax/__init__.py
qujax/densitytensor.py
qujax/densitytensor_observable.py
qujax/gates.py
qujax/statetensor.py
qujax/statetensor_observable.py
qujax/utils.py
qujax/version.py
qujax-1.1.0.dist-info/LICENSE
qujax-1.1.0.dist-info/METADATA
qujax-1.1.0.dist-info/WHEEL
qujax-1.1.0.dist-info/top_level.txt
qujax-1.1.0.dist-info/RECORD
