Metadata-Version: 2.1
Name: qujax
Version: 1.1.0
Summary: Simulating quantum circuits with JAX
Home-page: https://github.com/CQCL/qujax
Author: Sam Duffield
Author-email: sam.duffield@quantinuum.com
License: Apache 2
Platform: any
Classifier: Programming Language :: Python
Classifier: Intended Audience :: Developers
Classifier: Intended Audience :: Science/Research
Classifier: Topic :: Scientific/Engineering
Requires-Python: >=3.8
License-File: LICENSE
Requires-Dist: jax
Requires-Dist: jaxlib
